zope.app.dependable-5.0-py3.9-nspkg.pth
zope/app/dependable/__init__.py
zope/app/dependable/configure.zcml
zope/app/dependable/dependency.py
zope/app/dependable/interfaces.py
zope/app/dependable/tests.py
zope.app.dependable-5.0.dist-info/LICENSE.txt
zope.app.dependable-5.0.dist-info/METADATA
zope.app.dependable-5.0.dist-info/WHEEL
zope.app.dependable-5.0.dist-info/namespace_packages.txt
zope.app.dependable-5.0.dist-info/top_level.txt
zope.app.dependable-5.0.dist-info/RECORD
